memoshelve/__init__.py
memoshelve-1.0.5.dist-info/licenses/LICENSE
memoshelve-1.0.5.dist-info/METADATA
memoshelve-1.0.5.dist-info/WHEEL
memoshelve-1.0.5.dist-info/top_level.txt
memoshelve-1.0.5.dist-info/RECORD
