Metadata-Version: 2.4
Name: memoshelve
Version: 1.0.5
Summary: Add your description here
Project-URL: Homepage, https://github.com/jxnl/memoshelve
Project-URL: Bug Tracker, https://github.com/jxnl/memoshelve/issues
Requires-Python: >=3.11
License-File: LICENSE
Provides-Extra: robust
Requires-Dist: dill>=0.4.0; extra == "robust"
Requires-Dist: stablehash>=0.2.3; extra == "robust"
Requires-Dist: typing-extensions>=4.14.1; extra == "robust"
Provides-Extra: testing
Requires-Dist: numpy>=2.3.2; extra == "testing"
Requires-Dist: pytest>=8.4.1; extra == "testing"
Requires-Dist: pytest-asyncio>=1.1.0; extra == "testing"
Requires-Dist: memoshelve[robust]; extra == "testing"
Provides-Extra: dev
Requires-Dist: pre-commit>=4.2.0; extra == "dev"
Requires-Dist: memoshelve[testing]; extra == "dev"
Provides-Extra: all
Requires-Dist: memoshelve[dev,robust,testing]; extra == "all"
Dynamic: license-file
